[{
    "title": "#FuckinHipsters",
    "artist": "Tim Ski",
    "tracks": [{
        "title": "Two Door Cinema Club - Something Good Can Work",
        "url": "music/th77.mp3"
    },
    {
        "title": "Chairlift - Bruises",
        "url": "music/ffgh.mp3"
    },
    {
        "title": "Foster The People - I Would Do Anything For You",
        "url": "music/brt4.mp3"
    },
    {
        "title": "The Naked And Famous - Punching In A Dream",
        "url": "music/p345.mp3"
    },
    {
        "title": "Dale Earnhardt Jr. Jr. - If You Didn't See Me",
        "url": "music/yo44.mp3"
    },
    {
        "title": "Amanda Palmer - Want It Back",
        "url": "music/ght3.mp3"
    },
    {
        "title": "LadyHawke - Paris Is Burning",
        "url": "music/adfg.mp3"
    },
    {
        "title": "St. Vincent - Cruel",
        "url": "music/x123.mp3"
    },
    {
        "title": "Two Door Cinema Club - Undercover Martyn",
        "url": "music/2345.mp3"
    },
    {
        "title": "Phoenix - Lasso",
        "url": "music/ert5.mp3"
    }]
}]
